plugins/__init__.py
plugins/input_plugin.py
plugins/opengl_plugin.py
sage/__init__.py
sage/main.py
sage/core/__init__.py
sage/core/core.py
sage/plugins/__init__.py
sage/plugins/plugin_template.py
sage/plugins/plugins_config.json
sage/plugins/simple_plugin.py
SAGE_Core_X-0.1.1.dist-info/LICENSE
SAGE_Core_X-0.1.1.dist-info/METADATA
SAGE_Core_X-0.1.1.dist-info/WHEEL
SAGE_Core_X-0.1.1.dist-info/top_level.txt
SAGE_Core_X-0.1.1.dist-info/RECORD
